[
  {
    "id": 4,
    "cvFilePath": "uploads\\cvs\\1748097591939-AzizeSalmaResume_VF.pdf",
    "videoFilePath": null,
    "nom": "test1",
    "prenom": "test1",
    "email": "test1@gmail.com",
    "phoneNumber": "0600000000",
    "address": "Rabat",
    "tfidfScore": 5.56
  },
  {
    "id": 2,
    "cvFilePath": "uploads\\cvs\\1748093543403-Blue_Simple_Professional_CV_Resume.pdf",
    "videoFilePath": "uploads\\cvs\\1748093783574-A_Good_Elevator_Pitch_Example.mp4",
    "nom": "salma",
    "prenom": "salma",
    "email": "test1@gmail.com",
    "phoneNumber": "0600000000",
    "address": "Casablanca",
    "tfidfScore": 0.0
  }
]